kadai8/sel.v
module sel(input [15:0] a, b, input s, output logic [15:0] o);
	always_comb
		if(s) o = b;
		else o = a;
endmodule

kadai8/dmem.v

module dmem(input [7:0] ad, input [15:0] wd, input we, output [15:0] rd, input clk);
	logic [15:0] dm [255:0];
	assign rd = dm[ad];
	always @(posedge clk) begin
		if(we) dm[ad] <= wd;
	end
endmodule

kadai8/pu.vh
`define ASSERT 1'b1
`define NEGATE 1'b0

`define WIDTH 15 // data width 15:0
`define HALFWIDTH 7 // half data width 7:0

`define RAS 3 // 3:0 r0, r1, r2, r3 register addresses size
`define RASB 1 // 1:0 register address size bit for addressing

`define OPS 2 // 2:0 operator size

`define ADD 3'b000
`define THB 3'b010

`define PCS 5 // 5:0 program counter size
`define PCPRFXS 1 // 1:0 1:0+5:0=7:0

//`define CMDS 9 // 9:0 command size  HALT + RASB+1 + OPS+1 + RASB+1 + RASB+1
`define CMDS `WIDTH // see dec.v
`define LICMDS 1 // 1:0 00,01 do nothing 10 load low 11 load high

`define LIDXS 1 // 1:0 00,01 do nothing / 10 LIL / 11 LIH

`define DMS 255  // 255:0 data memory size
`define DMSB 7 // 7:0 data memory addr size

kadai8/dec.v
`include "pu.vh"
`define DEBUG
//`define DEBUG2

module dec(input [`CMDS:0] o, output logic h, we, output logic [`RASB:0] wad,
	output logic [`OPS:0] op, output logic [`RASB:0] brad, arad,
	output logic [`LICMDS:0] liop, output logic [`HALFWIDTH:0] iv,
	output logic pcwe, dmwe, dms, pcs, dstb,
	input ze, ca, sg);
/*
// F E D C B A 9 8 7 6 5 4 3 2 1 0
// 0 0 0 0 0 0 * * * * * * * * * 0 ; NOP (0) DSTB
// 0 0 0 0 0 0 * * * * * * * * * 1 ; HALT (1)
// 0 0 0 0 0 1 * * * * * * * * * * ; future reserved (PUSH, POP, SET(reg))
// 0 0 0 0 1 0 rw> F op--> a-> b-> ; CAL rw=ra,brad (F=0:NORM/1:DSTB) MV
// 0 0 0 0 1 1 * * * op--> a-> b-> ; EVA CAL ra,rb (F=0)/CMP ra,rb
// 0 0 0 1 0 0 f f p op--> a-> b-> ; JP/BR fp [ra op rb] (ff:NC,Z,C,S)
// 0 0 0 1 0 1 * * * * * * * * * * ; future reserved
// 0 0 0 1 1 0 F * * op--> a-> b-> ; SM [ra]=rb / SM [ra] = [ra op rb] *MM
// 0 0 0 1 1 1 rw> F op--> a-> b-> ; LM rw=[ra op rb] / LM rw=[rb] *MM
// 0 0 1 # rw> a-> im------------> ; CAL rw=ra,im (#=0:ADD/1:SUB only)
// 0 1 0 p 0 * f f im------------> ; JP/BR fp [(s)im]
// 0 1 0 * 1 0 b-> im------------> ; SM [(s)im]=rb *MM
// 0 1 0 p 1 1 f f im------------> ; JP/BR fp [PC + (s)im]
// 0 1 1 p a-> f f im------------> ; JP/BR fp [ra + (s)im]
// 1 0 0 0 rw> 0 0 0 0 0 0 0 S C Z ; LI rw,SM S:sign C:carry Z:zero
// 1 0 0 0 rw> 0 1 im------------> ; LI rw,(s)im (rw=rb) lidx=o[9:8]
// 1 0 0 0 rw> 1 0 im------------> ; LIL rw,im (rw=rb)
// 1 0 0 0 rw> 1 1 im------------> ; LIH rw,im (rw=rb)
// 1 0 0 1 rw> * * im------------> ; LM rw=[im] *MM
// 1 0 1 0 rw> a-> im------------> ; LM rw=[ra + (s)im]
// 1 0 1 1 a-> b-> im------------> ; SM [ra + (s)im]=rb
// 1 1 * * * * * * * * * * * * * * ; future reserved *MM
*/

	parameter THU =2'b00, IMM =2'b01, LIL =2'b10 ,LIH =2'b11;
	parameter UC =2'b00, ZE =2'b01, CA =2'b10, SG =2'b11;
	logic f1, f2;
	always @* begin
		f1 = `NEGATE;
		f2 = `NEGATE;
		case(o[9:8])
		// synopsys full_case parallel_case
		UC: begin
			f1 = `ASSERT;
			f2 = `ASSERT;
		end
		ZE: begin
			f1 = ~ze^o[7];
			f2 = ~ze^o[12];
		end
		CA: begin
			f1 = ~ca^o[7];
			f2 = ~ca^o[12];
		end
		SG: begin
			f1 = ~sg^o[7];
			f2 = ~sg^o[12];
		end
		endcase
	end

	always @* begin
		h = `NEGATE;
		arad = 0;
		brad = 0;
		op = `THB;
		we = `NEGATE;
		wad = 0;
		liop = THU;
		iv = 0;
		dstb = `NEGATE;
		pcwe = `NEGATE;
		dmwe = `NEGATE;
		dms = `NEGATE;
		pcs = `NEGATE;
		case(o[15:13])
		//synopsys full case parallel case
			3'b000:begin
				case(o[12:11])
				// synopsys full_case parallel_case
					2'b00:
					if(o[0]) h = `ASSERT;
// 0 0 0 0 0 0 * * * * * * * * * 1 ; HALT (1)
					else dstb = `ASSERT;
// 0 0 0 0 0 0 * * * * * * * * * 0 ; NOP (0) DSTB
					2'b01: begin
						arad = o[3:2];
						brad = o[1:0];
						op = o[6:4];
// 0 0 0 0 1 1 * * * op--> a-> b-> ; EVA CAL ra,rb (F=0)/CMP ra,rb
						if(o[10] == `NEGATE)begin
							wad = o[9:8];
							we = `ASSERT;
// 0 0 0 0 1 0 rw> F op--> a-> b-> ; CAL rw=ra,rb (F=0:NORM) MV
						end
					end
					2'b10:begin
						arad = o[3:2];
						brad = o[1:0];
						op = o[6:4];
					if(f1== `ASSERT) pcwe = `ASSERT;
// 0 0 0 1 0 0 f f p op--> a-> b-> ; JP/BR fp [ra op rb] (ff:NC,Z,C,S)
					end
					2'b11:begin
						if(o[10])begin
						wad = o[9:8];
						we = `ASSERT;
						op = o[6:4];
						arad = o[3:2];
						brad = o[1:0];
						dms = `ASSERT;
					end
// 0 0 0 1 1 1 rw> F op--> a-> b-> ; LM rw=[ra op rb] / LM rw=[rb] *MM
				else begin
					dmwe = `ASSERT;
					arad = o[3:2];
					brad = o[1:0];
					liop = IMM;
					iv = 8'd0;
					op = o[6:4];
				end
// 0 0 0 1 1 0 F * * op--> a-> b-> ; SM [ra]=rb / SM [ra] = [ra op rb] *MM
				end
				endcase
			end
			3'b001:begin
					wad = o[11:10];
					we = `ASSERT;
					arad = o[9:8];
					liop = IMM;
					iv = o[`HALFWIDTH:0];
					if(o[12]) op = 3'b001;
					else op = 3'b000;
			end
// 0 0 1 # rw> a-> im------------> ; CAL rw=ra,im (#=0:ADD/1:SUB only)
			3'b010:begin
				if(o[11] == 0)begin
					liop = IMM;
					iv = o[`HALFWIDTH:0];
					if(f2 == `ASSERT) pcwe = `ASSERT;
				end
// 0 1 0 p 0 * f f im------------> ; JP/BR fp [(s)im]
				else begin
					if(o[10])begin
						pcs = `ASSERT;
						liop = IMM;
						iv = o[`HALFWIDTH:0];
						op = 3'b000; //add
						if(f2 == `ASSERT) pcwe = `ASSERT;
					end
// 0 1 0 p 1 1 f f im------------> ; JP/BR fp [PC + (s)im]
					else begin
						dmwe = `ASSERT;
						brad = o[9:8];
						liop = IMM;
						iv = o[`HALFWIDTH:0];
					end
// 0 1 0 * 1 0 b-> im------------> ; SM [(s)im]=rb *MM
				end
			end

			3'b011:begin
				arad = o[11:10];
				liop = IMM;
				iv = o[`HALFWIDTH:0];
				op = 3'b000; //add
				if(f2 == `ASSERT) pcwe = `ASSERT;
			end
// 0 1 1 p a-> f f im------------> ; JP/BR fp [ra + (s)im]
			3'b100:begin
				if(o[12])begin //LM[im]
							wad = o[11:10];
							we = `ASSERT;
							liop = IMM;
							iv = o[`HALFWIDTH:0];
							dms = `ASSERT;
				end
// 1 0 0 1 rw> * * im------------> ; LM rw=[im] *MM
				else begin
					case(o[9:8])
							// synopsys full_case parallel_case
					2'b01:begin
						liop = o[9:8];
						iv = o[`HALFWIDTH:0];
						wad = o[11:10];
						we = `ASSERT;
					end
// 1 0 0 0 rw> 0 1 im------------> ; LI rw,(s)im (rw=rb) lidx=o[9:8]
					2'b10:begin
						brad = o[11:10];
						wad = o[11:10];
						we =  `ASSERT;
						liop = LIL;
						iv = o[`HALFWIDTH:0];
					end
// 1 0 0 0 rw> 1 0 im------------> ; LIL rw,im (rw=rb)
					2'b11:begin
						brad = o[11:10];
						wad = o[11:10];
						we =  `ASSERT;
						liop = LIH;
						iv = o[`HALFWIDTH:0];
					end
// 1 0 0 0 rw> 1 1 im------------> ; LIH rw,im (rw=rb)
					endcase
				end
			end
			3'b101:begin
				if(o[12])begin
					dmwe = `ASSERT;
					arad = o[11:10];
					brad = o[9:8];
					liop = IMM;
					iv = o[`HALFWIDTH:0];
					op = 3'b000;
				end
// 1 0 1 1 a-> b-> im------------> ; SM [ra + (s)im]=rb
				else begin
					wad = o[11:10];
					we = `ASSERT;
					arad = o[9:8];
					liop = IMM;
					iv = o[`HALFWIDTH:0];
					op = 3'b000;//add
					dms = `ASSERT;
				end
// 1 0 1 0 rw> a-> im------------> ; LM rw=[ra + (s)im]
			end
		endcase
	end
endmodule

kadai8/imem.v
`include "pu.vh"
module imem(input [`PCS:0] pc, output logic [`CMDS:0] o);
	always_comb
		case(pc)
		// synopsys full_case parallel_case
			6'h00:o = 16'b1000_0001_0000_0011; //LI rw,(s)im (rw= 0) lidx= THU, r0<- 3
            6'h01:o = 16'b0100_1000_0000_0000; //SM [(s)im]= 16'd0 *MM nn, mem[0]<-3
            6'h02:o = 16'b1000_0101_0000_0000; //LI rw,(s)im (rw= 1) lidx= THU,r1<-0
            6'h03:o = 16'b0100_1001_0000_0001; //SM [(s)im]= 16'd1 *MM nn, mem[1]<-r1
            6'h04:o = 16'b1000_1001_0000_0010; //LI rw,(s)im (rw= 2) lidx= THU, r2<-2
            6'h05:o = 16'b0100_1010_0000_0010; //SM [(s)im]= 16'd2 *MM nn, mem[2]<-r2
            6'h06:o = 16'b1001_0000_0000_1110; //SM [ra + (s)im]=rb, mem[17]<-r0

            6'h07:o = 16'b0000_1011_0000_0001; //CAL rw= 16'bra,rb (F= 16'b0:NORM)  r3<-r0+r1
            6'h08:o = 16'b1001_0000_0001_0001; //LM rw=[im] *MM, r0<-mem[17]
            6'h09:o = 16'b0001_1000_0010_0011; //SM [ra]=rb, mem[ro]<-r3
            6'h0a:o = 16'b1000_1001_0000_1111; //LI rw,(s)im (rw= r2) lidx= THU, r2<-15
            6'h0b:o = 16'b0001_0001_1001_0010; //JP/BR fp [ra op rb] r0, r2(ff:NC,Z,C,S)

            6'h0c:o = 16'b0010_0000_0000_0001; // CAL rw=ra,im, r0=r0+1
            6'h0d:o = 16'b0100_1001_0000_0001; //SM [(s)im]= 16'd1 *MM nn, mem[17]=r0
            6'h0e:o = 16'b0000_1010_0010_0011; //CAL rw=brad, r2=r3
            6'h0f:o = 16'b1010_0001_1111_1110; // LM rw=[ra + (s)im], r1 <-mem[r0-2]
            6'h10:o = 16'b1010_0000_1111_1101; //LM rw=[ra + (s)im], r0 <-mem[r0-3]
            6'h11:o = 16'b0100_1100_1111_0110; //JP/BR fp [PC + (s)im]
            6'h12:o = 16'b0000_0000_0000_0001; //HALT*/
		endcase
endmodule

/*
// F E D C B A 9 8 7 6 5 4 3 2 1 0
// 0 0 0 0 0 0 * * * * * * * * * 0 ; NOP (0) DSTB
// 0 0 0 0 0 0 * * * * * * * * * 1 ; HALT (1)
// 0 0 0 0 0 1 * * * * * * * * * * ; future reserved (PUSH, POP, SET(reg))
// 0 0 0 0 1 0 rw> F op--> a-> b-> ; CAL rw=ra,rb (F=0:NORM/1:DSTB) MV
// 0 0 0 0 1 1 * * * op--> a-> b-> ; EVA CAL ra,rb (F=0)/CMP ra,rb
// 0 0 0 1 0 0 f f p op--> a-> b-> ; JP/BR pf [ra op rb] (ff:NC,Z,C,S)
// 0 0 0 1 0 1 * * * * * * * * * * ; future reserved
// 0 0 0 1 1 0 F * * op--> a-> b-> ; SM [ra]=rb / SM [ra] = [ra op rb] *MM
// 0 0 0 1 1 1 rw> F op--> a-> b-> ; LM rw=[ra op rb] / LM rw=[rb] *MM
// 0 0 1 # rw> a-> im------------> ; CAL rw=ra,im (#=0:ADD/1:SUB only)
// 0 1 0 p 0 * f f im------------> ; JP/BR pf [(s)im]
// 0 1 0 * 1 0 b-> im------------> ; SM [(s)im]=rb *MM
// 0 1 0 p 1 1 f f im------------> ; JP/BR fp [PC + (s)im]
// 0 1 1 p a-> f f im------------> ; JP/BR fp [ra + (s)im]
// 1 0 0 0 rw> 0 0 0 0 0 0 0 S C Z ; LI rw,SM S:sign C:carry Z:zero
// 1 0 0 0 rw> 0 1 im------------> ; LI rw,(s)im (rw=rb) lidx=o[9:8]
// 1 0 0 0 rw> 1 0 im------------> ; LIL rw,im (rw=rb)
// 1 0 0 0 rw> 1 1 im------------> ; LIH rw,im (rw=rb)
// 1 0 0 1 rw> * * im------------> ; LM rw=[im] *MM
// 1 0 1 0 rw> a-> im------------> ; LM rw=[ra + (s)im]
// 1 0 1 1 a-> b-> im------------> ; SM [ra + (s)im]=rb
// 1 1 0 * * * * * * * * * * * * * ; future reserved *MM
// 1 1 1 * * * * * * * * * * * * * ; future reserved *MM (debug)
//
// ALU  000:ADD, 001:SUB, 010:THB, 011:ASR,
//      100:RSL, 101:RSL, 110:NAD, 111:XOR
//
// COND(ff) 00:UC 01:ZE 10:CA 11:SG
// P/N (p)  0:N(!=) 1:P(==)
//
// EX: Positive Zero => PZ
//
// SPECIALS
// F E D C B A 9 8 7 6 5 4 3 2 1 0
// 0 0 0 0 1 0 rw> 0 0 1 0 0 0 b-> ; MV rw=rb
// 1 0 0 0 rw> 0 1 0 0 0 0 0 0 0 0 ; RESET rw (LI rw=0)
// 0 0 1 0 rw> rw> 0 0 0 0 0 0 0 1 ; INC rw
// 0 0 1 1 rw> rw> 0 0 0 0 0 0 0 1 ; DEC rw
// 0 0 1 0 rw> ra> 0 0 0 0 0 0 0 1 ; INC rw=ra (rw = ra+1)
// 0 0 1 1 rw> ra> 0 0 0 0 0 0 0 1 ; DEC rw=ra (rw = ra-1)
// 0 0 0 0 1 1 * * * 0 0 1 a-> b-> ; CMP ra,rb (EVA SUB ra,rb)
*/

kadai8/pc.v

module pc(input halt, output logic [5:0] pc, input we, input [5:0] jpc, input clk, rst);
	always @(posedge clk or posedge rst)
		if(rst) pc <= 0;
		else if(!halt) begin
			if(we == 1'b1) pc <= jpc;
			else pc <= pc + 1;
		end
endmodule

kadai8/alu.v
`include "pu.vh"

module alu(input [`WIDTH:0] a, b, input [`OPS:0] op, output logic [`WIDTH:0] r,
		input dstb, output logic ze, ca, sg, input clk, rst);
	parameter ADD = 3'b000, SUB = 3'b001, THB = 3'b010, ASR = 3'b011;
	parameter RSR = 3'b100, RSL = 3'b101, NAD = 3'b110, XOR = 3'b111;
	logic [`WIDTH+1:0] rr;
	always @* begin
		case(op)
		// synopsys full_case parallel_case
		ADD: rr = a+b;
		SUB: rr = a-b;
		THB: rr = b;
		ASR: rr = a>>>b;
		RSR: rr = a>>b;
		RSL: rr = a<<b;
		NAD: rr = ~(a&b);
		XOR: rr = a^b;
		endcase
	end
	assign r = rr[`WIDTH:0];
	always @(posedge clk or posedge rst) begin
		if(rst) begin
			ze <= `NEGATE;
			ca <= `NEGATE;
			sg <= `NEGATE;
		end else begin
			if(r == 0) ze <= `ASSERT;
			else ze <= `NEGATE;
			if(r[`WIDTH] == 1'b1) sg <= `ASSERT;
			else sg <= `NEGATE;
			if(rr[`WIDTH+1] == 1'b1) ca <= `ASSERT;
			else ca <= `NEGATE;
		end
	end
endmodule

kadai8/lidx.v
`include "pu.vh"
module lidx(input [`WIDTH:0] i, input [`HALFWIDTH:0] iv, input [`LIDXS:0] op, output logic [`WIDTH:0] o);
	parameter THU =2'b00, IMM =2'b01, LIL =2'b10 ,LIH =2'b11;
	always @*
		casex(op)
		// synopsys full_case parallel_case
		THU:
			o = i;
		IMM:
			o = {{8{iv[`HALFWIDTH]}},iv[`HALFWIDTH:0]};
		LIL:
			o = {i[`WIDTH:`HALFWIDTH+1],iv};
		LIH:
			o = {iv,i[`HALFWIDTH:0]};
		endcase
endmodule

kadai8/rega.v
module rega(input logic [1:0] arad, brad, output logic [15:0] a, b,
	input we, input logic [1:0] wad, input [15:0] wd,
	input clk, rst);
	logic [15:0] regar [3:0];
	always @(posedge clk or posedge rst) begin
		if(rst) begin
			regar[0] <= 0;
			regar[1] <= 0;
			regar[2] <= 0;
			regar[3] <= 0;
		end else if(we) regar[wad] <= wd;
	end
	assign a = regar[arad];
	assign b = regar[brad];
endmodule

kadai8/pu.v
module pu(output we, output logic [15:0] rwd, input clk, rst);
	logic [15:0] a, b, ao, bo, lp, mrd;
	logic [7:0] iv;
	logic [1:0] arad, brad, wad;
	logic [2:0] op;
	logic [5:0] pca;
	logic [15:0] o;
	logic [1:0] liop;
	rega rega(arad, brad, a, b, we, wad, rwd, clk, rst);
	sel asel(a, {{(15-5){1'b0}},pca}, pcs, ao);
	lidx lidx(b, iv, liop, bo);
	alu alu(ao, bo, op, lp, dstb, ze, ca, sg, clk, rst);
	pc pc(h, pca, pcwe, rwd[5:0], clk, rst);
	imem imem(pca, o);
	dec dec(o, h, we, wad, op, brad, arad, liop, iv,
		pcwe, dmwe, dms, pcs, dstb, ze, ca, sg);
	dmem dmem(lp[7:0], b, dmwe, mrd, clk);
	sel dsel(lp, mrd, dms, rwd);
endmodule

kadai8/test.v

module test;
	logic clk, rst;
	logic [15:0] wd;
	pu pu(we, wd, clk, rst);
	always #2 clk =~ clk;
initial begin
$dumpfile("pu.vcd");
$dumpvars(0, pu);
rst = 1;
clk = 0;
#0
rst = 0;
#2000
$finish;
end
endmodule

kadai8/pu.vcd
$date
	Sun Jul 12 17:49:40 2020
$end
$version
	Icarus Verilog
$end
$timescale
	1s
$end
$scope module test $end
$scope module pu $end
$var wire 1 ! clk $end
$var wire 1 " rst $end
$var wire 1 # ze $end
$var wire 1 $ we $end
$var wire 2 % wad [1:0] $end
$var wire 1 & sg $end
$var wire 16 ' rwd [15:0] $end
$var wire 1 ( pcwe $end
$var wire 1 ) pcs $end
$var wire 6 * pca [5:0] $end
$var wire 3 + op [2:0] $end
$var wire 16 , o [15:0] $end
$var wire 16 - mrd [15:0] $end
$var wire 16 . lp [15:0] $end
$var wire 2 / liop [1:0] $end
$var wire 8 0 iv [7:0] $end
$var wire 1 1 h $end
$var wire 1 2 dstb $end
$var wire 1 3 dmwe $end
$var wire 1 4 dms $end
$var wire 1 5 ca $end
$var wire 2 6 brad [1:0] $end
$var wire 16 7 bo [15:0] $end
$var wire 16 8 b [15:0] $end
$var wire 2 9 arad [1:0] $end
$var wire 16 : ao [15:0] $end
$var wire 16 ; a [15:0] $end
$scope module alu $end
$var wire 1 ! clk $end
$var wire 1 " rst $end
$var wire 16 < r [15:0] $end
$var wire 3 = op [2:0] $end
$var wire 1 2 dstb $end
$var wire 16 > b [15:0] $end
$var wire 16 ? a [15:0] $end
$var reg 1 5 ca $end
$var reg 17 @ rr [16:0] $end
$var reg 1 & sg $end
$var reg 1 # ze $end
$upscope $end
$scope module asel $end
$var wire 16 A b [15:0] $end
$var wire 1 ) s $end
$var wire 16 B a [15:0] $end
$var reg 16 C o [15:0] $end
$upscope $end
$scope module dec $end
$var wire 1 5 ca $end
$var wire 1 & sg $end
$var wire 1 # ze $end
$var wire 16 D o [15:0] $end
$var reg 2 E arad [1:0] $end
$var reg 2 F brad [1:0] $end
$var reg 1 4 dms $end
$var reg 1 3 dmwe $end
$var reg 1 2 dstb $end
$var reg 1 G f1 $end
$var reg 1 H f2 $end
$var reg 1 1 h $end
$var reg 8 I iv [7:0] $end
$var reg 2 J liop [1:0] $end
$var reg 3 K op [2:0] $end
$var reg 1 ) pcs $end
$var reg 1 ( pcwe $end
$var reg 2 L wad [1:0] $end
$var reg 1 $ we $end
$upscope $end
$scope module dmem $end
$var wire 8 M ad [7:0] $end
$var wire 1 ! clk $end
$var wire 16 N rd [15:0] $end
$var wire 1 3 we $end
$var wire 16 O wd [15:0] $end
$upscope $end
$scope module dsel $end
$var wire 16 P a [15:0] $end
$var wire 16 Q b [15:0] $end
$var wire 1 4 s $end
$var reg 16 R o [15:0] $end
$upscope $end
$scope module imem $end
$var wire 6 S pc [5:0] $end
$var reg 16 T o [15:0] $end
$upscope $end
$scope module lidx $end
$var wire 8 U iv [7:0] $end
$var wire 2 V op [1:0] $end
$var wire 16 W i [15:0] $end
$var reg 16 X o [15:0] $end
$upscope $end
$scope module pc $end
$var wire 1 ! clk $end
$var wire 1 1 halt $end
$var wire 6 Y jpc [5:0] $end
$var wire 1 " rst $end
$var wire 1 ( we $end
$var reg 6 Z pc [5:0] $end
$upscope $end
$scope module rega $end
$var wire 16 [ a [15:0] $end
$var wire 2 \ arad [1:0] $end
$var wire 16 ] b [15:0] $end
$var wire 2 ^ brad [1:0] $end
$var wire 1 ! clk $end
$var wire 1 " rst $end
$var wire 2 _ wad [1:0] $end
$var wire 16 ` wd [15:0] $end
$var wire 1 $ we $end
$upscope $end
$upscope $end
$upscope $end
$enddefinitions $end
#0
$dumpvars
b11 `
b0 _
b0 ^
b0 ]
b0 \
b0 [
b0 Z
b11 Y
b11 X
b0 W
b1 V
b11 U
b1000000100000011 T
b0 S
b11 R
bx Q
b11 P
b0 O
bx N
b11 M
b0 L
b10 K
b1 J
b11 I
1H
1G
b0 F
b0 E
b1000000100000011 D
b0 C
b0 B
b0 A
b11 @
b0 ?
b11 >
b10 =
b11 <
b0 ;
b0 :
b0 9
b0 8
b11 7
b0 6
05
04
03
02
01
b11 0
b1 /
b11 .
bx -
b1000000100000011 ,
b10 +
b0 *
0)
0(
b11 '
0&
b0 %
1$
0#
1"
0!
$end
#5
1!
#10
0!
#15
1!
#20
0!
0"
#25
b0 Y
b0 M
b0 '
b0 R
b0 `
b0 .
b0 <
b0 P
b0 @
b0 7
b0 >
b0 X
13
b0 0
b0 I
b0 U
b1 /
b1 J
b1 V
0$
1H
1G
b100100000000000 ,
b100100000000000 D
b100100000000000 T
b11 :
b11 ?
b11 C
b1 A
b1 *
b1 S
b1 Z
b11 ;
b11 B
b11 [
b11 8
b11 O
b11 W
b11 ]
1!
#30
0!
#35
1$
b1 %
b1 L
b1 _
03
b1 /
b1 J
b1 V
0H
0G
b1000010100000000 ,
b1000010100000000 D
b1000010100000000 T
1#
b10 A
b10 *
b10 S
b10 Z
b11 -
b11 N
b11 Q
1!
#40
0!
#45
b1 Y
bx -
bx N
bx Q
b1 M
b1 '
b1 R
b1 `
b1 .
b1 <
b1 P
b1 @
b1 7
b1 >
b1 X
b1 0
b1 I
b1 U
b0 8
b0 O
b0 W
b0 ]
b1 6
b1 F
b1 ^
13
b1 /
b1 J
b1 V
b0 %
b0 L
b0 _
0$
b100100100000001 ,
b100100100000001 D
b100100100000001 T
b11 A
b11 *
b11 S
b11 Z
1!
#50
0!
#55
b10 Y
b10 M
b10 '
b10 R
b10 `
b10 .
b10 <
b10 P
b10 @
b10 7
b10 >
b10 X
1$
b10 %
b10 L
b10 _
03
b10 0
b10 I
b10 U
b1 /
b1 J
b1 V
b11 8
b11 O
b11 W
b11 ]
b0 6
b0 F
b0 ^
1H
1G
b1000100100000010 ,
b1000100100000010 D
b1000100100000010 T
0#
b100 A
b100 *
b100 S
b100 Z
bx -
bx N
bx Q
1!
#60
0!
#65
b10 8
b10 O
b10 W
b10 ]
b10 6
b10 F
b10 ^
13
b10 0
b10 I
b10 U
b1 /
b1 J
b1 V
b0 %
b0 L
b0 _
0$
1H
1G
b100101000000010 ,
b100101000000010 D
b100101000000010 T
b101 A
b101 *
b101 S
b101 Z
1!
#70
0!
#75
bx Y
bx '
bx R
bx `
b1110 M
b1110 .
b1110 <
b1110 P
b1110 @
b1110 7
b1110 >
b1110 X
14
1$
03
b1110 0
b1110 I
b1110 U
b1 /
b1 J
b1 V
b11 8
b11 O
b11 W
b11 ]
b0 6
b0 F
b0 ^
1H
1G
b1001000000001110 ,
b1001000000001110 D
b1001000000001110 T
b110 A
b110 *
b110 S
b110 Z
bx -
bx N
bx Q
1!
#80
0!
#85
bx M
bx .
bx <
bx P
bx Y
bx @
bx '
bx R
bx `
b0 7
b0 >
b0 X
b11 %
b11 L
b11 _
b0 +
b0 =
b0 K
b1 6
b1 F
b1 ^
04
b0 0
b0 I
b0 U
b0 /
b0 J
b0 V
1$
1H
1G
b101100000001 ,
b101100000001 D
b101100000001 T
bx :
bx ?
bx C
b111 A
b111 *
b111 S
b111 Z
bx ;
bx B
bx [
b0 8
b0 O
b0 W
b0 ]
1!
#90
0!
#95
b10001 M
b10001 .
b10001 <
b10001 P
b10001 @
b10001 7
b10001 >
b10001 X
14
b10001 0
b10001 I
b10001 U
b1 /
b1 J
b1 V
b0 %
b0 L
b0 _
1$
b10 +
b10 =
b10 K
bx 8
bx O
bx W
bx ]
b0 6
b0 F
b0 ^
1H
1G
b1001000000010001 ,
b1001000000010001 D
b1001000000010001 T
b1000 A
b1000 *
b1000 S
b1000 Z
1!
#100
0!
#105
b11 -
b11 N
b11 Q
b0 M
b0 .
b0 <
b0 P
b0 Y
b0 @
b0 '
b0 R
b0 `
b0 7
b0 >
b0 X
b11 6
b11 F
b11 ^
13
04
b0 0
b0 I
b0 U
b1 /
b1 J
b1 V
0$
1H
1G
b1100000100011 ,
b1100000100011 D
b1100000100011 T
b1001 A
b1001 *
b1001 S
b1001 Z
1!
#110
0!
#115
b1111 Y
b1111 M
b1111 '
b1111 R
b1111 `
b1111 .
b1111 <
b1111 P
b1111 @
b1111 7
b1111 >
b1111 X
1$
b10 %
b10 L
b10 _
b1111 0
b1111 I
b1111 U
03
b1 /
b1 J
b1 V
b0 6
b0 F
b0 ^
0H
0G
b1000100100001111 ,
b1000100100001111 D
b1000100100001111 T
1#
b1010 A
b1010 *
b1010 S
b1010 Z
bx -
bx N
bx Q
1!
#120
0!
#125
bx Y
bx M
bx '
bx R
bx `
bx .
bx <
bx P
bx @
0(
b1 +
b1 =
b1 K
b1111 8
b1111 O
b1111 W
b1111 ]
b10 6
b10 F
b10 ^
b0 0
b0 I
b0 U
b0 /
b0 J
b0 V
b0 %
b0 L
b0 _
0$
b1000110010010 ,
b1000110010010 D
b1000110010010 T
0H
0G
b1011 A
b1011 *
b1011 S
b1011 Z
0#
1!
#130
0!
#135
b1 7
b1 >
b1 X
b1 0
b1 I
b1 U
b1 /
b1 J
b1 V
1$
b0 +
b0 =
b0 K
bx 8
bx O
bx W
bx ]
b0 6
b0 F
b0 ^
1H
1G
b10000000000001 ,
b10000000000001 D
b10000000000001 T
b1100 A
b1100 *
b1100 S
b1100 Z
1!
#140
0!
#145
b1 Y
b0 -
b0 N
b0 Q
b1 M
b1 '
b1 R
b1 `
b1 .
b1 <
b1 P
b1 @
b0 8
b0 O
b0 W
b0 ]
b1 6
b1 F
b1 ^
13
b1 0
b1 I
b1 U
b1 /
b1 J
b1 V
0$
b10 +
b10 =
b10 K
1H
1G
b100100100000001 ,
b100100100000001 D
b100100100000001 T
b1101 A
b1101 *
b1101 S
b1101 Z
1!
#150
0!
#155
bx Y
bx -
bx N
bx Q
bx M
bx '
bx R
bx `
bx .
bx <
bx P
b0xxxxxxxxxxxxxxxx @
bx 7
bx >
bx X
1$
b10 %
b10 L
b10 _
03
b0 0
b0 I
b0 U
b0 /
b0 J
b0 V
bx 8
bx O
bx W
bx ]
b11 6
b11 F
b11 ^
1H
1G
b101000100011 ,
b101000100011 D
b101000100011 T
b1110 A
b1110 *
b1110 S
b1110 Z
1!
#160
0!
#165
b11111110 M
b1111111111111110 .
b1111111111111110 <
b1111111111111110 P
b1111111111111110 @
b1111111111111110 7
b1111111111111110 >
b1111111111111110 X
b0 :
b0 ?
b0 C
14
b0 +
b0 =
b0 K
b11111110 0
b11111110 I
b11111110 U
b1 /
b1 J
b1 V
b0 ;
b0 B
b0 [
b1 9
b1 E
b1 \
b0 %
b0 L
b0 _
1$
b0 6
b0 F
b0 ^
1H
0G
b1010000111111110 ,
b1010000111111110 D
b1010000111111110 T
b1111 A
b1111 *
b1111 S
b1111 Z
1!
#170
0!
#175
bx M
bx .
bx <
bx P
b1111111111111101 7
b1111111111111101 >
b1111111111111101 X
bx @
bx :
bx ?
bx C
14
b11111101 0
b11111101 I
b11111101 U
b1 /
b1 J
b1 V
1$
b0 +
b0 =
b0 K
bx ;
bx B
bx [
b0 9
b0 E
b0 \
1G
1H
b1010000011111101 ,
b1010000011111101 D
b1010000011111101 T
1&
b10000 A
b10000 *
b10000 S
b10000 Z
1!
#180
0!
#185
b111 Y
b111 M
b111 '
b111 R
b111 `
b111 .
b111 <
b111 P
b10000000000000111 @
b10001 :
b10001 ?
b10001 C
b1111111111110110 7
b1111111111110110 >
b1111111111110110 X
1(
1)
04
b11110110 0
b11110110 I
b11110110 U
b1 /
b1 J
b1 V
0$
b0 +
b0 =
b0 K
b100110011110110 ,
b100110011110110 D
b100110011110110 T
1H
1G
b10001 A
b10001 *
b10001 S
b10001 Z
0&
1!
#190
0!
#195
bx Y
bx M
bx '
bx R
bx `
bx .
bx <
bx P
b0 7
b0 >
b0 X
bx @
1$
b11 %
b11 L
b11 _
b0 8
b0 O
b0 W
b0 ]
b1 6
b1 F
b1 ^
0)
0(
b0 0
b0 I
b0 U
b0 /
b0 J
b0 V
b0 +
b0 =
b0 K
1H
1G
bx :
bx ?
bx C
b101100000001 ,
b101100000001 D
b101100000001 T
15
b111 A
b111 *
b111 S
b111 Z
1!
#200
0!
#205
b10001 M
b10001 .
b10001 <
b10001 P
b10001 @
b10001 7
b10001 >
b10001 X
14
b10001 0
b10001 I
b10001 U
b1 /
b1 J
b1 V
b0 %
b0 L
b0 _
1$
b10 +
b10 =
b10 K
bx 8
bx O
bx W
bx ]
b0 6
b0 F
b0 ^
b1001000000010001 ,
b1001000000010001 D
b1001000000010001 T
1H
1G
b1000 A
b1000 *
b1000 S
b1000 Z
05
1!
#210
0!
